odoo/addons/web_datetime_picker_default_time/README.rst
odoo/addons/web_datetime_picker_default_time/__init__.py
odoo/addons/web_datetime_picker_default_time/__manifest__.py
odoo/addons/web_datetime_picker_default_time/i18n/it.po
odoo/addons/web_datetime_picker_default_time/i18n/web_datetime_picker_default_time.pot
odoo/addons/web_datetime_picker_default_time/readme/CONTRIBUTORS.md
odoo/addons/web_datetime_picker_default_time/readme/CREDITS.md
odoo/addons/web_datetime_picker_default_time/readme/DESCRIPTION.md
odoo/addons/web_datetime_picker_default_time/readme/ROADMAP.md
odoo/addons/web_datetime_picker_default_time/readme/USAGE.md
odoo/addons/web_datetime_picker_default_time/static/description/icon.png
odoo/addons/web_datetime_picker_default_time/static/description/index.html
odoo/addons/web_datetime_picker_default_time/static/src/js/datepicker.esm.js
odoo/addons/web_datetime_picker_default_time/static/src/js/datetime_field.esm.js
odoo/addons/web_datetime_picker_default_time/static/tests/web_datetime_picker_default_time.test.js
odoo_addon_web_datetime_picker_default_time-18.0.1.0.0.2.dist-info/METADATA
odoo_addon_web_datetime_picker_default_time-18.0.1.0.0.2.dist-info/WHEEL
odoo_addon_web_datetime_picker_default_time-18.0.1.0.0.2.dist-info/top_level.txt
odoo_addon_web_datetime_picker_default_time-18.0.1.0.0.2.dist-info/RECORD
